rsLoggerTwo/__init__.py
rsLoggerTwo/logger.py
rsLoggerTwo-1.1.0.dist-info/LICENSE
rsLoggerTwo-1.1.0.dist-info/METADATA
rsLoggerTwo-1.1.0.dist-info/WHEEL
rsLoggerTwo-1.1.0.dist-info/entry_points.txt
rsLoggerTwo-1.1.0.dist-info/top_level.txt
rsLoggerTwo-1.1.0.dist-info/RECORD
